mcp_stock_server/__init__.py
mcp_stock_server/main.py
mcp_stock_server-0.0.2.dist-info/METADATA
mcp_stock_server-0.0.2.dist-info/WHEEL
mcp_stock_server-0.0.2.dist-info/entry_points.txt
mcp_stock_server-0.0.2.dist-info/top_level.txt
mcp_stock_server-0.0.2.dist-info/RECORD
