Metadata-Version: 2.4
Name: mcp_stock_server
Version: 0.0.2
Summary: An MCP server that provides stock prices using yfinance and curl_cffi
Author-email: joekoz <joekozhaya@yahoo.com>
License: MIT
Requires-Python: >=3.11
Requires-Dist: fastmcp
Requires-Dist: yfinance
Requires-Dist: curl_cffi
